MANIFEST.in
README.md
setup.py
aimed_xnat/__init__.py
aimed_xnat/central.cfg
aimed_xnat/xnat-struct.txt
aimed_xnat.egg-info/PKG-INFO
aimed_xnat.egg-info/SOURCES.txt
aimed_xnat.egg-info/dependency_links.txt
aimed_xnat.egg-info/requires.txt
aimed_xnat.egg-info/top_level.txt
aimed_xnat/core/__init__.py
aimed_xnat/core/sess.py
aimed_xnat/data/__init__.py
aimed_xnat/data/downloader.py
aimed_xnat/data/explorer.py
aimed_xnat/data/uploader.py
aimed_xnat/extras/__init__.py
aimed_xnat/extras/util.py
docs/__init__.py
docs/conf.py