Metadata-Version: 2.1
Name: aimed-xnat
Version: 1.0
Summary: XNAT data manipulation tools
Home-page: https://github.com/KiLJ4EdeN/aimed_xnat
Author: Abdolkarim Saeedi
Author-email: parsa592323@gmail.com
License: Apache-2.0
Download-URL: https://github.com/KiLJ4EdeN/aimed_xnatreleases/tag/v_01
Keywords: medical,xnat,under-development
Platform: UNKNOWN
